billy/__init__.py
billyng-0.1.16.dist-info/METADATA
billyng-0.1.16.dist-info/WHEEL
billyng-0.1.16.dist-info/top_level.txt
billyng-0.1.16.dist-info/RECORD
