Metadata-Version: 2.1
Name: billyng
Version: 0.1.16
Summary: Python SDK for the Billy microservice
Home-page: https://github.com/f1ps1
Author: Philipp Scheer
Author-email: hi@fipsi.at
License: UNKNOWN
Platform: UNKNOWN
Classifier: Development Status :: 2 - Pre-Alpha
Classifier: Topic :: Office/Business :: Financial
Classifier: Topic :: Office/Business :: Financial :: Accounting
Classifier: Programming Language :: Python :: 3
Classifier: License :: OSI Approved :: MIT License
Classifier: Operating System :: POSIX :: Linux
Classifier: Operating System :: MacOS
Requires-Python: >=3.6
Requires-Dist: certifi (==2022.6.15)
Requires-Dist: charset-normalizer (==2.1.0)
Requires-Dist: idna (==3.3)
Requires-Dist: requests (==2.28.1)
Requires-Dist: urllib3 (==1.26.11)
